LICENSE
MANIFEST.in
README.md
pyproject.toml
setup.cfg
setup.py
globlocks/__init__.py
globlocks/apps.py
globlocks/choices.py
globlocks/colors.py
globlocks/fonts.py
globlocks/panels.py
globlocks/preview.py
globlocks/rt_extensions.py
globlocks/settings.py
globlocks/staticfiles.py
globlocks/tests.py
globlocks/util.py
globlocks.egg-info/PKG-INFO
globlocks.egg-info/SOURCES.txt
globlocks.egg-info/dependency_links.txt
globlocks.egg-info/requires.txt
globlocks.egg-info/top_level.txt
globlocks/blocks/__init__.py
globlocks/blocks/richtext.py
globlocks/blocks/utils.py
globlocks/blocks/bases/__init__.py
globlocks/blocks/bases/baseblock.py
globlocks/blocks/bases/template.py
globlocks/blocks/bases/visibility.py
globlocks/blocks/block_fields/__init__.py
globlocks/blocks/block_fields/justify.py
globlocks/blocks/block_fields/orderable_block.py
globlocks/blocks/block_fields/colorblock/__init__.py
globlocks/blocks/block_fields/colorblock/colorblock.py
globlocks/blocks/block_fields/fontpicker/__init__.py
globlocks/blocks/block_fields/fontpicker/fontpicker.py
globlocks/blocks/block_fields/rangeslider/__init__.py
globlocks/blocks/block_fields/rangeslider/rangeslider.py
globlocks/blocks/block_fields/toolbar/__init__.py
globlocks/blocks/block_fields/toolbar/bar.py
globlocks/blocks/block_fields/toolbar/element.py
globlocks/blocks/block_fields/toolbar/toolbar_field.py
globlocks/blocks/block_fields/toolbar/toolbar_widget.py
globlocks/blocks/block_fields/toolbar/tools.py
globlocks/blocks/components/__init__.py
globlocks/blocks/components/heading.py
globlocks/blocks/components/image.py
globlocks/blocks/components/image_text.py
globlocks/blocks/components/link.py
globlocks/blocks/components/text.py
globlocks/blocks/components/menus/__init__.py
globlocks/blocks/components/menus/flat.py
globlocks/blocks/components/menus/layered.py
globlocks/fields/__init__.py
globlocks/fields/colorfield.py
globlocks/fields/fontfield.py
globlocks/fields/orderablefield.py
globlocks/locale/en/LC_MESSAGES/django.mo
globlocks/locale/en/LC_MESSAGES/django.po
globlocks/locale/nl/LC_MESSAGES/django.mo
globlocks/locale/nl/LC_MESSAGES/django.po
